filepong/__init__.py
filepong-0.0.0.dist-info/LICENSE
filepong-0.0.0.dist-info/METADATA
filepong-0.0.0.dist-info/WHEEL
filepong-0.0.0.dist-info/RECORD
