Metadata-Version: 2.1
Name: filepong
Version: 0.0.0
Summary: Dual pane file manager with TUI
License: BSD-2
Author: Mac Prible
Author-email: prible@gmail.com.com
Requires-Python: >=3.10,<4.0
Classifier: License :: Other/Proprietary License
Classifier: Programming Language :: Python :: 3
Classifier: Programming Language :: Python :: 3.10
Classifier: Programming Language :: Python :: 3.11
Requires-Dist: 0 (>=0.0.0,<0.0.1)
Requires-Dist: textual (>=0.35.1,<0.36.0)
